sync2asyncio
