Metadata-Version: 2.1
Name: sync2asyncio
Version: 0.3
Summary: convert sync to asyncio 
Home-page: https://github.com/ydf0509/sync2asyncio
Author: bfzs
Author-email: ydf0509@sohu.com
Maintainer: ydf
Maintainer-email: ydf0509@sohu.com
License: BSD License
Keywords: asyncio,async,sync
Platform: all
Classifier: Development Status :: 4 - Beta
Classifier: Operating System :: OS Independent
Classifier: Intended Audience :: Developers
Classifier: License :: OSI Approved :: BSD License
Classifier: Programming Language :: Python
Classifier: Programming Language :: Python :: Implementation
Classifier: Programming Language :: Python :: 3.6
Classifier: Programming Language :: Python :: 3.7
Classifier: Programming Language :: Python :: 3.8
Classifier: Programming Language :: Python :: 3.9
Classifier: Topic :: Software Development :: Libraries
